.editorconfig
.env
.gitignore
LICENSE
MANIFEST.in
Pipfile
Pipfile.lock
README.md
azure-pipelines.yml
setup.py
tox.ini
.vscode/extensions.json
.vscode/settings.json
brewblox_emitter/__init__.py
brewblox_emitter/__main__.py
brewblox_emitter/relay.py
brewblox_emitter.egg-info/PKG-INFO
brewblox_emitter.egg-info/SOURCES.txt
brewblox_emitter.egg-info/dependency_links.txt
brewblox_emitter.egg-info/requires.txt
brewblox_emitter.egg-info/top_level.txt
docker/.gitignore
docker/amd/Dockerfile
docker/arm/Dockerfile
test/__init__.py
test/conftest.py
test/test_main.py
test/test_relay.py