Metadata-Version: 2.1
Name: brewblox-emitter
Version: 0.1.1.dev11
Summary: UNKNOWN
Home-page: https://github.com/BrewBlox/brewblox-emitter
Author: BrewPi
Author-email: development@brewpi.com
License: UNKNOWN
Keywords: brewing brewpi brewblox embedded plugin service
Platform: UNKNOWN
Classifier: Development Status :: 4 - Beta
Classifier: License :: OSI Approved :: GNU General Public License (GPL)
Classifier: Programming Language :: Python :: 3.8
Classifier: Intended Audience :: End Users/Desktop
Classifier: Topic :: System :: Hardware
Requires-Python: >=3.8
